README.rst
setup.py
chevah/__init__.py
chevah/keycert/__init__.py
chevah/keycert/common.py
chevah/keycert/exceptions.py
chevah/keycert/sexpy.py
chevah/keycert/ssh.py
chevah/keycert/ssl.py
chevah/keycert/tests/__init__.py
chevah/keycert/tests/helpers.py
chevah/keycert/tests/keydata.py
chevah/keycert/tests/test_exceptions.py
chevah/keycert/tests/test_ssh.py
chevah/keycert/tests/test_ssl.py
chevah_keycert.egg-info/PKG-INFO
chevah_keycert.egg-info/SOURCES.txt
chevah_keycert.egg-info/dependency_links.txt
chevah_keycert.egg-info/entry_points.txt
chevah_keycert.egg-info/namespace_packages.txt
chevah_keycert.egg-info/requires.txt
chevah_keycert.egg-info/top_level.txt