Metadata-Version: 1.1
Name: chevah-keycert
Version: 1.4.4
Summary: SSH Keys and SSL keys and certificates management.
Home-page: https://github.com/chevah/chevah-keycert
Author: Adi Roiban
Author-email: adiroiban@gmail.com
License: MIT
Keywords: twisted ssh ssl tls pki ca
Platform: UNKNOWN
Classifier: Development Status :: 5 - Production/Stable
Classifier: Intended Audience :: Developers
Classifier: Topic :: Software Development :: Build Tools
Classifier: License :: OSI Approved :: MIT License
Classifier: Programming Language :: Python :: 2
Classifier: Programming Language :: Python :: 2.7
